MANIFEST.in
ez_setup.py
setup.py
WSGIRewrite.egg-info/PKG-INFO
WSGIRewrite.egg-info/SOURCES.txt
WSGIRewrite.egg-info/dependency_links.txt
WSGIRewrite.egg-info/entry_points.txt
WSGIRewrite.egg-info/requires.txt
WSGIRewrite.egg-info/top_level.txt
WSGIRewrite.egg-info/zip-safe
docs/AUTHORS
docs/Changelog
docs/FAQ
docs/INSTALL
docs/LICENSE
docs/LIMITATIONS
docs/NEWS
docs/README
docs/THANKS
docs/TODO
examples/homepage.max.html
examples/homepage.max2.html
examples/homepage.min.html
examples/homepage.std.html
examples/htaccess
examples/server.ini
tests/test_basic.py
wsgirewrite/__init__.py
wsgirewrite/rewrite.py
